{
  "id": 8693,
  "title": "The Man in the Arena",
  "updated_at": "2018-08-24T06:10:13.421Z",
  "created_at": "2012-03-20T04:16:08.416Z",
  "state": "available",
  "comment_count": 0,
  "generated_title": "The Man in the Arena",
  "content_html": "<blockquote><p>\"It is not the critic who counts; not the man who points out how the strong man stumbles, or where the doer of deeds could have done them better. The credit belongs to the man who is actually in the arena, whose face is marred by dust and sweat and blood; who strives valiantly; who errs, who comes short again and again, because there is no effort without error and shortcoming; but who does actually strive to do the deeds; who knows great enthusiasms, the great devotions; who spends himself in a worthy cause; who at the best knows in the end the triumph of high achievement, and who at the worst, if he fails, at least fails while daring greatly, so that his place shall never be with those cold and timid souls who neither know victory nor defeat.\"</p></blockquote>",
  "description_html": "<p>Theodore Roosevelt<br>Excerpt from the speech \"Citizenship In A Republic\"<br><br>Delivered at the Sorbonne, in Paris, France on 23 April, 1910</p>",
  "visibility": "public",
  "content": "&gt; \"It is not the critic who counts; not the man who points out how the strong man stumbles, or where the doer of deeds could have done them better. The credit belongs to the man who is actually in the arena, whose face is marred by dust and sweat and blood; who strives valiantly; who errs, who comes short again and again, because there is no effort without error and shortcoming; but who does actually strive to do the deeds; who knows great enthusiasms, the great devotions; who spends himself in a worthy cause; who at the best knows in the end the triumph of high achievement, and who at the worst, if he fails, at least fails while daring greatly, so that his place shall never be with those cold and timid souls who neither know victory nor defeat.\"",
  "description": "Theodore Roosevelt\nExcerpt from the speech \"Citizenship In A Republic\"  \nDelivered at the Sorbonne, in Paris, France on 23 April, 1910",
  "source": null,
  "image": null,
  "embed": null,
  "attachment": null,
  "metadata": null,
  "base_class": "Block",
  "class": "Text",
  "user": {
    "id": 17,
    "created_at": "2011-06-21T01:41:32.390Z",
    "slug": "damon-zucconi",
    "username": "Damon Zucconi",
    "first_name": "Damon",
    "last_name": "Zucconi",
    "full_name": "Damon Zucconi",
    "avatar": "https://arena-avatars.s3.amazonaws.com/17/small_35df8fd928b7eefcf7ff673a50598412.png?1545489709",
    "avatar_image": {
      "thumb": "https://arena-avatars.s3.amazonaws.com/17/small_35df8fd928b7eefcf7ff673a50598412.png?1545489709",
      "display": "https://arena-avatars.s3.amazonaws.com/17/medium_35df8fd928b7eefcf7ff673a50598412.png?1545489709"
    },
    "channel_count": 588,
    "following_count": 1068,
    "profile_id": 105,
    "follower_count": 713,
    "initials": "DZ",
    "can_index": true,
    "metadata": {
      "description": "[damonzucconi.com](http://www.damonzucconi.com)\n[twitter.com/dzucconi](https://twitter.com/dzucconi)\n[instagram.com/damonzucconi](https://www.instagram.com/damonzucconi/)"
    },
    "is_premium": true,
    "is_exceeding_private_connections_limit": false,
    "is_confirmed": true,
    "is_pending_reconfirmation": false,
    "is_pending_confirmation": false,
    "badge": "premium",
    "base_class": "User",
    "class": "User"
  },
  "connections": [
    {
      "id": 110,
      "title": "J. Stuart Moore",
      "created_at": "2011-07-05T21:09:54.490Z",
      "updated_at": "2019-01-15T12:14:57.332Z",
      "added_to_at": "2013-03-21T13:51:07.235Z",
      "published": true,
      "open": true,
      "collaboration": false,
      "slug": "j-stuart-moore",
      "length": 30,
      "kind": "profile",
      "status": "public",
      "user_id": 1,
      "metadata": null,
      "share_link": null,
      "user": {
        "id": 1,
        "created_at": "2011-06-21T01:41:30.326Z",
        "slug": "j-stuart-moore",
        "username": "J. Stuart Moore",
        "first_name": "J. Stuart",
        "last_name": "Moore",
        "full_name": "J. Stuart Moore",
        "avatar": "https://gravatar.com/avatar/fe93438144f0c586afbf6172694eacdc.png?d=blank&r=r&s=150",
        "avatar_image": {
          "thumb": "https://gravatar.com/avatar/fe93438144f0c586afbf6172694eacdc.png?d=blank&r=r&s=40",
          "display": "https://gravatar.com/avatar/fe93438144f0c586afbf6172694eacdc.png?d=blank&r=r&s=150"
        },
        "channel_count": 375,
        "following_count": 145,
        "profile_id": 110,
        "follower_count": 79,
        "initials": "JSM",
        "can_index": true,
        "metadata": null,
        "is_premium": true,
        "is_exceeding_private_connections_limit": false,
        "is_confirmed": true,
        "is_pending_reconfirmation": false,
        "is_pending_confirmation": false,
        "badge": "premium",
        "base_class": "User",
        "class": "User"
      },
      "group": null,
      "base_class": "Channel"
    },
    {
      "id": 275,
      "title": "Arena Influences",
      "created_at": "2011-08-12T17:53:48.000Z",
      "updated_at": "2019-01-31T09:07:31.293Z",
      "added_to_at": "2018-12-30T18:17:22.483Z",
      "published": true,
      "open": false,
      "collaboration": true,
      "slug": "arena-influences",
      "length": 125,
      "kind": "default",
      "status": "closed",
      "user_id": 15,
      "metadata": {
        "description": " *We are as gods and might as well get good at it.*  - Stewart Brand\n"
      },
      "share_link": "SEmJuHb",
      "user": {
        "id": 15,
        "created_at": "2011-06-21T01:41:32.080Z",
        "slug": "charles-broskoski",
        "username": "Charles Broskoski",
        "first_name": "Charles",
        "last_name": "Broskoski",
        "full_name": "Charles Broskoski",
        "avatar": "https://arena-avatars.s3.amazonaws.com/15/small_ac34fd3f9a2b4484f015946f5be05967.png?1543198252",
        "avatar_image": {
          "thumb": "https://arena-avatars.s3.amazonaws.com/15/small_ac34fd3f9a2b4484f015946f5be05967.png?1543198252",
          "display": "https://arena-avatars.s3.amazonaws.com/15/medium_ac34fd3f9a2b4484f015946f5be05967.png?1543198252"
        },
        "channel_count": 413,
        "following_count": 4663,
        "profile_id": 111,
        "follower_count": 1515,
        "initials": "CB",
        "can_index": true,
        "metadata": {
          "description": "[Are.na](http://are.na) co-founder ✍︎\n\nhttp://charlesbroskoski.com\n"
        },
        "is_premium": true,
        "is_exceeding_private_connections_limit": false,
        "is_confirmed": true,
        "is_pending_reconfirmation": false,
        "is_pending_confirmation": false,
        "badge": "premium",
        "base_class": "User",
        "class": "User"
      },
      "group": {
        "id": 289,
        "class": "Group",
        "base_class": "Group",
        "created_at": "2018-07-10T18:07:08.664Z",
        "updated_at": "2019-01-08T18:06:10.827Z",
        "name": "Are.na Team",
        "description": "",
        "visibility": 0
      },
      "base_class": "Channel"
    },
    {
      "id": 2647,
      "title": "Killer Quotes",
      "created_at": "2012-05-19T22:07:36.826Z",
      "updated_at": "2019-01-29T23:49:32.997Z",
      "added_to_at": "2019-01-20T17:44:53.136Z",
      "published": true,
      "open": true,
      "collaboration": false,
      "slug": "killer-quotes",
      "length": 114,
      "kind": "default",
      "status": "public",
      "user_id": 14,
      "metadata": null,
      "share_link": "rmBrFpE",
      "user": {
        "id": 14,
        "created_at": "2011-06-21T01:41:31.855Z",
        "slug": "john-michael-boling",
        "username": "John Michael Boling",
        "first_name": "John Michael",
        "last_name": "Boling",
        "full_name": "John Michael Boling",
        "avatar": "https://arena-avatars.s3.amazonaws.com/14/small_05bc87b82ddc3b7972ad5fa04e146372.png?1373980507",
        "avatar_image": {
          "thumb": "https://arena-avatars.s3.amazonaws.com/14/small_05bc87b82ddc3b7972ad5fa04e146372.png?1373980507",
          "display": "https://arena-avatars.s3.amazonaws.com/14/medium_05bc87b82ddc3b7972ad5fa04e146372.png?1373980507"
        },
        "channel_count": 1016,
        "following_count": 1603,
        "profile_id": 106,
        "follower_count": 768,
        "initials": "JMB",
        "can_index": true,
        "metadata": null,
        "is_premium": true,
        "is_exceeding_private_connections_limit": false,
        "is_confirmed": true,
        "is_pending_reconfirmation": false,
        "is_pending_confirmation": false,
        "badge": "premium",
        "base_class": "User",
        "class": "User"
      },
      "group": null,
      "base_class": "Channel"
    },
    {
      "id": 36375,
      "title": "107",
      "created_at": "2015-11-11T07:55:32.905Z",
      "updated_at": "2019-01-25T02:10:02.268Z",
      "added_to_at": "2017-12-29T18:13:09.862Z",
      "published": true,
      "open": true,
      "collaboration": false,
      "slug": "one-zero-seven",
      "length": 258,
      "kind": "default",
      "status": "public",
      "user_id": 8595,
      "metadata": null,
      "share_link": null,
      "user": {
        "id": 8595,
        "created_at": "2015-11-05T08:19:54.301Z",
        "slug": "casey-silverstein",
        "username": "Casey Silverstein",
        "first_name": "Casey",
        "last_name": "Silverstein",
        "full_name": "Casey Silverstein",
        "avatar": "https://arena-avatars.s3.amazonaws.com/8595/small_5f198b7f694f16b2266777ae94527573.jpg?1447228030",
        "avatar_image": {
          "thumb": "https://arena-avatars.s3.amazonaws.com/8595/small_5f198b7f694f16b2266777ae94527573.jpg?1447228030",
          "display": "https://arena-avatars.s3.amazonaws.com/8595/medium_5f198b7f694f16b2266777ae94527573.jpg?1447228030"
        },
        "channel_count": 24,
        "following_count": 17,
        "profile_id": 36034,
        "follower_count": 11,
        "initials": "CS",
        "can_index": true,
        "metadata": null,
        "is_premium": false,
        "is_exceeding_private_connections_limit": false,
        "is_confirmed": true,
        "is_pending_reconfirmation": false,
        "is_pending_confirmation": false,
        "badge": null,
        "base_class": "User",
        "class": "User"
      },
      "group": null,
      "base_class": "Channel"
    },
    {
      "id": 88445,
      "title": "Connection",
      "created_at": "2017-08-16T14:35:23.128Z",
      "updated_at": "2019-01-01T07:42:30.165Z",
      "added_to_at": "2017-12-19T13:07:02.712Z",
      "published": true,
      "open": false,
      "collaboration": false,
      "slug": "connection-1502964317",
      "length": 5,
      "kind": "default",
      "status": "closed",
      "user_id": 17358,
      "metadata": null,
      "share_link": null,
      "user": {
        "id": 17358,
        "created_at": "2017-07-03T21:06:10.377Z",
        "slug": "jess-gilliland",
        "username": "Jess Gilliland",
        "first_name": "Jess",
        "last_name": "Gilliland",
        "full_name": "Jess Gilliland",
        "avatar": "https://gravatar.com/avatar/502ca75f9f1fda49d7841513cef235ce.png?d=blank&r=r&s=150",
        "avatar_image": {
          "thumb": "https://gravatar.com/avatar/502ca75f9f1fda49d7841513cef235ce.png?d=blank&r=r&s=40",
          "display": "https://gravatar.com/avatar/502ca75f9f1fda49d7841513cef235ce.png?d=blank&r=r&s=150"
        },
        "channel_count": 65,
        "following_count": 63,
        "profile_id": 81633,
        "follower_count": 16,
        "initials": "JG",
        "can_index": true,
        "metadata": null,
        "is_premium": false,
        "is_exceeding_private_connections_limit": false,
        "is_confirmed": true,
        "is_pending_reconfirmation": false,
        "is_pending_confirmation": false,
        "badge": null,
        "base_class": "User",
        "class": "User"
      },
      "group": null,
      "base_class": "Channel"
    },
    {
      "id": 178015,
      "title": "Lernmaterial",
      "created_at": "2018-04-10T16:07:07.853Z",
      "updated_at": "2019-01-30T05:32:01.849Z",
      "added_to_at": "2019-01-17T16:26:18.426Z",
      "published": true,
      "open": false,
      "collaboration": false,
      "slug": "lernmaterial",
      "length": 70,
      "kind": "default",
      "status": "closed",
      "user_id": 14585,
      "metadata": {
        "description": "A channel to challenge me to learn more, to expand knowledge across different fields and areas. "
      },
      "share_link": null,
      "user": {
        "id": 14585,
        "created_at": "2017-03-24T09:26:33.556Z",
        "slug": "marten-anton",
        "username": "Marten Anton",
        "first_name": "Marten",
        "last_name": "Anton",
        "full_name": "Marten Anton",
        "avatar": "https://arena-avatars.s3.amazonaws.com/14585/small_ab677dd2f29b909df32a7975a50d1c8b.jpg?1523549805",
        "avatar_image": {
          "thumb": "https://arena-avatars.s3.amazonaws.com/14585/small_ab677dd2f29b909df32a7975a50d1c8b.jpg?1523549805",
          "display": "https://arena-avatars.s3.amazonaws.com/14585/medium_ab677dd2f29b909df32a7975a50d1c8b.jpg?1523549805"
        },
        "channel_count": 64,
        "following_count": 136,
        "profile_id": 69635,
        "follower_count": 12,
        "initials": "MA",
        "can_index": false,
        "metadata": {
          "description": "Creative:\nwww.10-6.co\nFashion/Design/Education/Humour:\nwww.ozeane.co\n"
        },
        "is_premium": true,
        "is_exceeding_private_connections_limit": false,
        "is_confirmed": true,
        "is_pending_reconfirmation": false,
        "is_pending_confirmation": false,
        "badge": "investor",
        "base_class": "User",
        "class": "User"
      },
      "group": null,
      "base_class": "Channel"
    }
  ]
}
